nonebot_plugin_covid_19_by/123.ttf
nonebot_plugin_covid_19_by/__init__.py
nonebot_plugin_covid_19_by/config_covid_19.py
nonebot_plugin_covid_19_by/covid_19.txt
nonebot_plugin_covid_19_by-4.5.dist-info/METADATA
nonebot_plugin_covid_19_by-4.5.dist-info/WHEEL
nonebot_plugin_covid_19_by-4.5.dist-info/top_level.txt
nonebot_plugin_covid_19_by-4.5.dist-info/RECORD
