Metadata-Version: 2.1
Name: nonebot-plugin-covid-19-by
Version: 4.5
Summary: 疫情小助手 支持查地区 风险地区 境外输入等
Home-page: https://github.com/bingqiu456/nonebot_plugin_covid_19_by
Author: bingyue
Author-email: hello-yiqiu@qq.com
License: UNKNOWN
Keywords: nonebot_plugin_covid_19_by,nonebot,nonebot_plugin
Platform: UNKNOWN
Requires-Dist: aiofiles (>=0.8.0)
Requires-Dist: nonebot2 (>=2.0.0b2)
Requires-Dist: Pillow (>=9.1.1)
Requires-Dist: nonebot-adapter-onebot (>=2.0.0b1)
Requires-Dist: httpx (>=0.23.0)
